invenio_config_tuw/__init__.py
invenio_config_tuw/config.py
invenio_config_tuw/dmp.py
invenio_config_tuw/ext.py
invenio_config_tuw/logs.py
invenio_config_tuw/proxies.py
invenio_config_tuw/records.py
invenio_config_tuw/services.py
invenio_config_tuw/tasks.py
invenio_config_tuw/auth/__init__.py
invenio_config_tuw/auth/handlers.py
invenio_config_tuw/auth/settings.py
invenio_config_tuw/auth/utils.py
invenio_config_tuw/curations/__init__.py
invenio_config_tuw/curations/requests.py
invenio_config_tuw/curations/tasks.py
invenio_config_tuw/notifications/__init__.py
invenio_config_tuw/notifications/backends.py
invenio_config_tuw/notifications/builders.py
invenio_config_tuw/notifications/entity_resolvers.py
invenio_config_tuw/notifications/uow.py
invenio_config_tuw/permissions/__init__.py
invenio_config_tuw/permissions/generators.py
invenio_config_tuw/permissions/policies.py
invenio_config_tuw/startup/__init__.py
invenio_config_tuw/startup/config.py
invenio_config_tuw/startup/misc.py
invenio_config_tuw/tiss/__init__.py
invenio_config_tuw/tiss/models.py
invenio_config_tuw/tiss/tasks.py
invenio_config_tuw/tiss/utils.py
invenio_config_tuw/translations/.gitkeep
invenio_config_tuw/users/__init__.py
invenio_config_tuw/users/preferences.py
invenio_config_tuw/users/registration.py
invenio_config_tuw/users/schemas.py
invenio_config_tuw/users/utils.py
invenio_config_tuw/users/views.py
invenio_config_tuw/users/templates/curation_settings.html
invenio_config_tuw/users/templates/notifications_settings.html
invenio_config_tuw/users/templates/outreach_email.html
invenio_config_tuw/users/templates/outreach_email.txt
invenio_config_tuw/users/templates/invenio_notifications/email/acceptance-reminder.jinja
invenio_config_tuw/users/templates/invenio_notifications/email/group-notification.jinja
invenio_config_tuw/users/templates/invenio_notifications/email/metadata-edit.jinja
invenio_config_tuw/users/templates/invenio_notifications/email/record-publication.jinja
invenio_config_tuw-2026.0.0.dist-info/METADATA
invenio_config_tuw-2026.0.0.dist-info/WHEEL
invenio_config_tuw-2026.0.0.dist-info/entry_points.txt
invenio_config_tuw-2026.0.0.dist-info/licenses/AUTHORS.rst
invenio_config_tuw-2026.0.0.dist-info/licenses/LICENSE
invenio_config_tuw-2026.0.0.dist-info/RECORD
