Metadata-Version: 2.4
Name: Invenio-Config-TUW
Version: 2026.0.0
Summary: Workflow customizations and config overrides for TU Wien.
Project-URL: Repository, https://gitlab.tuwien.ac.at/crdm/invenio-config-tuw
Author-email: "Team of the Center for Research Data Management (TU Wien)" <tudata@tuwien.ac.at>
License-Expression: MIT
License-File: AUTHORS.rst
License-File: LICENSE
Keywords: configuration,invenio,tu wien
Classifier: Development Status :: 5 - Production/Stable
Classifier: Environment :: Web Environment
Classifier: License :: OSI Approved :: MIT License
Classifier: Operating System :: OS Independent
Classifier: Programming Language :: Python
Classifier: Programming Language :: Python :: 3.12
Classifier: Programming Language :: Python :: 3.13
Classifier: Topic :: Internet :: WWW/HTTP :: Dynamic Content
Classifier: Topic :: Software Development :: Libraries :: Python Modules
Requires-Python: >=3.12
Requires-Dist: flask-minify>=0.47
Requires-Dist: invenio-app-rdm>=13.0.0
Requires-Dist: invenio-curations>=0.2.0
Requires-Dist: invenio-damap>=0.2.0
Requires-Dist: invenio-search>=3.0.0
Provides-Extra: tests
Requires-Dist: httpretty>=1.1.4; extra == 'tests'
Requires-Dist: invenio-search[opensearch2]>=3.0.0; extra == 'tests'
Requires-Dist: ipdb>=0.13.13; extra == 'tests'
Requires-Dist: ipython>=8.18.1; extra == 'tests'
Requires-Dist: pytest-black>=0.3.0; extra == 'tests'
Requires-Dist: pytest-invenio>=3.0.0; extra == 'tests'
Requires-Dist: pytest-mock>=3.14.0; extra == 'tests'
Requires-Dist: pytest-ruff>=0.4.1; extra == 'tests'
